dajudge/__init__.py
dajudge-1.0.0.dist-info/licenses/LICENSE
dajudge-1.0.0.dist-info/METADATA
dajudge-1.0.0.dist-info/WHEEL
dajudge-1.0.0.dist-info/top_level.txt
dajudge-1.0.0.dist-info/RECORD
