Metadata-Version: 2.4
Name: dajudge
Version: 1.0.0
Summary: Japanese Pun (Dajare) detector
Author-email: Nemupy <me.nemupy@gmail.com>
License: MIT
Classifier: Programming Language :: Python :: 3
Classifier: Programming Language :: Python :: 3.8
Classifier: Programming Language :: Python :: 3.9
Classifier: Programming Language :: Python :: 3.10
Classifier: Programming Language :: Python :: 3.11
Classifier: Programming Language :: Python :: 3.12
Classifier: License :: OSI Approved :: MIT License
Classifier: Operating System :: OS Independent
Requires-Python: <3.13,>=3.8
License-File: LICENSE
Requires-Dist: sudachipy
Requires-Dist: sudachidict_core
Dynamic: license-file
